python_yeelightbt-0.0.4.dist-info/METADATA
python_yeelightbt-0.0.4.dist-info/RECORD
python_yeelightbt-0.0.4.dist-info/WHEEL
python_yeelightbt-0.0.4.dist-info/entry_points.txt
python_yeelightbt-0.0.4.dist-info/top_level.txt
yeelightbt/__init__.py
yeelightbt/cli.py
yeelightbt/connection.py
yeelightbt/lamp.py
yeelightbt/structures.py
yeelightbt/test.py
yeelightbt/version.py
